germalemma/__init__.py
germalemma/data/lemmata.pickle
germalemma-0.1.3.dist-info/LICENSE
germalemma-0.1.3.dist-info/METADATA
germalemma-0.1.3.dist-info/WHEEL
germalemma-0.1.3.dist-info/top_level.txt
germalemma-0.1.3.dist-info/RECORD
