Metadata-Version: 2.1
Name: germalemma
Version: 0.1.3
Summary: A lemmatizer for German language text.
Home-page: https://github.com/WZBSocialScienceCenter/germalemma
Author: Markus Konrad
Author-email: markus.konrad@wzb.eu
License: Apache 2.0
Project-URL: Source, https://github.com/WZBSocialScienceCenter/germalemma
Project-URL: Tracker, https://github.com/WZBSocialScienceCenter/germalemma/issues
Keywords: text lemmatization normalization textmining textanalysis mining preprocessing
Platform: UNKNOWN
Classifier: Development Status :: 4 - Beta
Classifier: Intended Audience :: Science/Research
Classifier: Intended Audience :: Developers
Classifier: License :: OSI Approved :: Apache Software License
Classifier: Operating System :: OS Independent
Classifier: Programming Language :: Python
Classifier: Programming Language :: Python :: 3
Classifier: Programming Language :: Python :: 3.6
Classifier: Programming Language :: Python :: 3.7
Classifier: Programming Language :: Python :: 3.8
Classifier: Topic :: Scientific/Engineering :: Information Analysis
Classifier: Topic :: Software Development :: Libraries :: Python Modules
Classifier: Topic :: Utilities
Requires-Python: >=3.6
